{"cameraMode":{"drawMode":0,"name":"Shaded","section":"Shading Mode"},"sceneLighting":false,"audioPlay":false,"sceneViewState":{"showFog":true,"showMaterialUpdate":false,"showSkybox":false,"showFlares":true,"showImageEffects":true,"showParticleSystems":true},"in2DMode":false,"pivot":{"x":0.016228556632995607,"y":0.5172600150108337,"z":0.015239298343658448},"rotation":{"x":0.3587295413017273,"y":0.573867917060852,"z":-0.30744171142578127,"w":0.6691159009933472},"size":2.856321334838867,"orthographic":false}